xingu/__init__.py
xingu/__main__.py
xingu/coach.py
xingu/config_manager.py
xingu/dataprovider.py
xingu/dataproviderfactory.py
xingu/estimator.py
xingu/model.py
xingu/estimators/catboost.py
xingu-1.7.3.dist-info/LICENSE
xingu-1.7.3.dist-info/METADATA
xingu-1.7.3.dist-info/WHEEL
xingu-1.7.3.dist-info/entry_points.txt
xingu-1.7.3.dist-info/top_level.txt
xingu-1.7.3.dist-info/RECORD
