Metadata-Version: 2.1
Name: xingu
Version: 1.7.3
Summary: Automated ML model training and packaging
Author-email: Avi Alkalay <avi@unix.sh>
License: GNU LESSER GENERAL PUBLIC LICENSE
Project-URL: Homepage, https://github.com/avibrazil/xingu
Project-URL: Source, https://github.com/avibrazil/xingu
Project-URL: Issues, https://github.com/avibrazil/xingu/issues/new/choose
Project-URL: Pypi, https://pypi.org/project/xingu
Keywords: mlengineering,xingu
Classifier: Intended Audience :: Developers
Classifier: Programming Language :: Python :: 3
Classifier: Operating System :: OS Independent
Classifier: License :: OSI Approved :: GNU Library or Lesser General Public License (LGPL)
Classifier: Development Status :: 5 - Production/Stable
Classifier: Intended Audience :: Science/Research
Classifier: Topic :: Scientific/Engineering :: Information Analysis
Requires-Python: >=3.8
License-File: LICENSE
Requires-Dist: pandas
Requires-Dist: python-decouple
Requires-Dist: SQLAlchemy
Requires-Dist: tabulate
Requires-Dist: pygit2
Requires-Dist: randomname
Requires-Dist: pyyaml
Requires-Dist: s3path
Requires-Dist: smart-open
Requires-Dist: scikit-learn
Provides-Extra: docs
Requires-Dist: sklearn ; extra == 'docs'
